<?xml version="1.0" encoding="UTF-8"?>
<databaseChangeLog
        xmlns="http://www.liquibase.org/xml/ns/dbchangelog"
        xmlns:xsi="http://www.w3.org/2001/XMLSchema-instance"
        xsi:schemaLocation="http://www.liquibase.org/xml/ns/dbchangelog
        https://www.liquibase.org/xml/ns/dbchangelog/dbchangelog-4.4.xsd">

    <include file="init/09/12.sql" relativeToChangelogFile="true"/>
    <include file="init/09/27.sql" relativeToChangelogFile="true"/>
    <include file="init/09/30.sql" relativeToChangelogFile="true"/>
    <include file="init/09/16.sql" relativeToChangelogFile="true"/>
    <include file="init/10/22.sql" relativeToChangelogFile="true"/>
    <include file="init/10/26.sql" relativeToChangelogFile="true"/>
    <include file="init/11/08.sql" relativeToChangelogFile="true"/>

    <include file="./data/09/12.sql" relativeToChangelogFile="true"/>
    <include file="./data/10/30.sql" relativeToChangelogFile="true"/>
</databaseChangeLog>